{
"dc_creator_sm": ["Metro Data Resource Center"],
"dc_description_s": "Major regional arterial streets derived from the streets layer for the Metro region.",
"dc_format_s": "Shapefile",
"dc_identifier_s": "geo.lclark.edu\/submit\/items\/show\/6",
"dc_publisher_s": "Metro Data Resource Center",
"dc_rights_s": "Public",
"dc_subject_sm": ["Streets"],
"dc_title_s": "Portland Major Arterials",
"dc_type_s": "Dataset",
"dct_isPartOf_sm": "RLIS",
"dct_provenance_s": "Lewis & Clark",
"dct_references_s": "{\"http://schema.org/url\":\"http://geo.lclark.edu/submit/items/show/6\",\"http://schema.org/downloadUrl\":\"http://drive.google.com/drive/folders/0B-249YJc4OukenlNRHFSOTh6WU0\",\"http://www.opengis.net/def/serviceType/ogc/wfs\":\"http://52.11.226.237:8080/geoserver/wfs\",\"http://www.opengis.net/def/serviceType/ogc/wms\":\"http://52.11.226.237:8080/geoserver/wms\"}",
"dct_spatial_sm": ["Portland, Oregon, United States"],
"dct_temporal_sm": ["2016"],
"layer_geom_type_s": "Line",
"layer_id_s": "RLIS:major_arterials",
"layer_modified_dt": "2016-8-11T22:35:30Z",
"layer_slug_s": "major_arterials",
"solr_geom": "ENVELOPE(-123.61491278047, -121.67705117671, 45.928619692655, 44.982625713468)"}
